{
	"configurations" : 
	[
		{
			"directories" : 
			[
				{
					"build" : ".",
					"jsonFile" : "directory-.-Debug-f5ebdc15457944623624.json",
					"minimumCMakeVersion" : 
					{
						"string" : "3.27"
					},
					"projectIndex" : 0,
					"source" : ".",
					"targetIndexes" : 
					[
						0
					]
				}
			],
			"name" : "Debug",
			"projects" : 
			[
				{
					"directoryIndexes" : 
					[
						0
					],
					"name" : "Treasure_island_game",
					"targetIndexes" : 
					[
						0
					]
				}
			],
			"targets" : 
			[
				{
					"directoryIndex" : 0,
					"id" : "Treasure_island_game::@6890427a1f51a3e7e1df",
					"jsonFile" : "target-Treasure_island_game-Debug-dd98ccb2f787a1e05629.json",
					"name" : "Treasure_island_game",
					"projectIndex" : 0
				}
			]
		}
	],
	"kind" : "codemodel",
	"paths" : 
	{
		"build" : "/home/locked31/CLionProjects/Treasure island game/cmake-build-debug",
		"source" : "/home/locked31/CLionProjects/Treasure island game"
	},
	"version" : 
	{
		"major" : 2,
		"minor" : 6
	}
}
